darlog/selenium_wrapper/__init__.py
darlog/selenium_wrapper/common.py
darlog/selenium_wrapper/defaults.py
darlog/selenium_wrapper/firefox.py
darlog_selenium_wrapper-0.0.1.dist-info/LICENSE.md
darlog_selenium_wrapper-0.0.1.dist-info/METADATA
darlog_selenium_wrapper-0.0.1.dist-info/WHEEL
darlog_selenium_wrapper-0.0.1.dist-info/top_level.txt
darlog_selenium_wrapper-0.0.1.dist-info/RECORD
